kor_mark_search/__init__.py
kor_mark_search/index_builder.py
kor_mark_search/index_search.py
kor_mark_search/markdown_utils.py
kor_mark_search/string_group.py
kor_mark_search/unicode_converter.py
kor_mark_search-0.1.0.dist-info/METADATA
kor_mark_search-0.1.0.dist-info/WHEEL
kor_mark_search-0.1.0.dist-info/RECORD
