Metadata-Version: 2.1
Name: kor-mark-search
Version: 0.1.0
Summary: A package suitable for searching queries in Korean-based Markdown, including features such as automatic typo correction.
Home-page: https://github.com/bill0077/kor-mark-search
License: MIT
Keywords: korean,markdown,search
Author: bill0077
Author-email: <bill007tjr@gmail.com>
Requires-Python: >=3.10,<4.0
Classifier: License :: OSI Approved :: MIT License
Classifier: Programming Language :: Python :: 3
Classifier: Programming Language :: Python :: 3.10
Classifier: Programming Language :: Python :: 3.11
Project-URL: Repository, https://github.com/bill0077/kor-mark-search
